jsonstruct/__init__.py
jsonstruct/cli.py
jsonstruct_cli-0.1.22.dist-info/METADATA
jsonstruct_cli-0.1.22.dist-info/WHEEL
jsonstruct_cli-0.1.22.dist-info/entry_points.txt
jsonstruct_cli-0.1.22.dist-info/top_level.txt
jsonstruct_cli-0.1.22.dist-info/RECORD
