Metadata-Version: 2.4
Name: jsonstruct-cli
Version: 0.1.22
Summary: Format deeply nested JSON and decode JWTs
Requires-Python: >=3.7
Requires-Dist: pyjwt
